setup.py
beeswarm/__init__.py
beeswarm/beeswarm.py
pybeeswarm.egg-info/PKG-INFO
pybeeswarm.egg-info/SOURCES.txt
pybeeswarm.egg-info/dependency_links.txt
pybeeswarm.egg-info/requires.txt
pybeeswarm.egg-info/top_level.txt