Metadata-Version: 1.1
Name: pybeeswarm
Version: 1.0.0
Summary: Beeswarm plots for python
Home-page: https://github.com/mgymrek/pybeeswarm
Author: Melissa Gymrek
Author-email: mgymrek@mit.edu
License: MIT
Download-URL: https://github.com/mgymrek/pybeeswarm
Platform: UNKNOWN
Classifier: Development Status :: 4 - Beta
Classifier: Programming Language :: Python :: 2.7
Classifier: License :: OSI Approved :: MIT License
Classifier: Operating System :: OS Independent
Classifier: Intended Audience :: Science/Research
Classifier: Topic :: Scientific/Engineering :: Visualization
